alien_ink/__init__.py
alien_ink/config.py
alien_ink/kagwrap.py
alien_ink/version.py
alien_ink-0.0.7.dist-info/LICENSE
alien_ink-0.0.7.dist-info/METADATA
alien_ink-0.0.7.dist-info/WHEEL
alien_ink-0.0.7.dist-info/top_level.txt
alien_ink-0.0.7.dist-info/RECORD
