Metadata-Version: 2.1
Name: alien-ink
Version: 0.0.7
Summary: Alien Ink - a personal machine learning toolkit
Home-page: https://github.com/codycollier/alien-ink
Author: Cody Collier
Author-email: cody@telnet.org
License: MIT
Keywords: artificial intelligence,machine learning
Classifier: Development Status :: 4 - Beta
Classifier: Intended Audience :: Developers
Classifier: Topic :: Scientific/Engineering :: Artificial Intelligence
Classifier: License :: OSI Approved :: MIT License
Classifier: Programming Language :: Python :: 3.6
License-File: LICENSE
Requires-Dist: kaggle
Requires-Dist: numpy
Requires-Dist: packaging
Requires-Dist: pandas
Requires-Dist: sklearn
Requires-Dist: tensorflow (>=2.9.1)
Requires-Dist: tensorflow-datasets
Requires-Dist: torch (>=1.6)
Requires-Dist: transformers
Requires-Dist: tqdm
